LICENSE
README.md
furiosa_models/__init__.py
furiosa_models/config.py
furiosa_models/dtype.py
furiosa_models/py.typed
furiosa_models/version.py
furiosa_models/architecture/__init__.py
furiosa_models/architecture/layers/__init__.py
furiosa_models/architecture/layers/activation.py
furiosa_models/architecture/layers/base.py
furiosa_models/architecture/layers/layernorm.py
furiosa_models/architecture/layers/linear.py
furiosa_models/architecture/layers/logits_processor.py
furiosa_models/architecture/layers/patch_embedding.py
furiosa_models/architecture/layers/rotary_embedding.py
furiosa_models/architecture/layers/vocab_embedding.py
furiosa_models/architecture/layers/ops/__init__.py
furiosa_models/architecture/layers/ops/activation.py
furiosa_models/architecture/layers/ops/base.py
furiosa_models/architecture/layers/ops/layernorm.py
furiosa_models/architecture/layers/ops/linear.py
furiosa_models/architecture/layers/ops/patch_embedding.py
furiosa_models/architecture/layers/ops/rotary_embedding.py
furiosa_models/architecture/layers/ops/vocab_embedding.py
furiosa_models/architecture/model_loader/__init__.py
furiosa_models/architecture/model_loader/weight_utils.py
furiosa_models/architecture/models/__init__.py
furiosa_models/architecture/models/llama.py
furiosa_models/architecture/models/mllama4.py
furiosa_models/architecture/models/qwen2.py
furiosa_models/architecture/models/utils.py
furiosa_models/architecture/models/serve/__init__.py
furiosa_models/architecture/models/serve/args.py
furiosa_models/architecture/models/serve/base.py
furiosa_models/architecture/models/serve/causal.py
furiosa_models/architecture/models/serve/utils.py
furiosa_models/architecture/models/serve/specs/__init__.py
furiosa_models/architecture/models/serve/specs/contexts.py
furiosa_models/architecture/models/serve/specs/dims.py
furiosa_models/architecture/models/serve/specs/dtypes.py
furiosa_models/architecture/models/serve/specs/inputs.py
furiosa_models/attention/__init__.py
furiosa_models_lang-2025.3.0.dist-info/METADATA
furiosa_models_lang-2025.3.0.dist-info/WHEEL
furiosa_models_lang-2025.3.0.dist-info/licenses/LICENSE
furiosa_models_lang-2025.3.0.dist-info/RECORD
